sik_llms/# Implementation Guide: Add Trace Contex.md
sik_llms/__init__.py
sik_llms/anthropic.py
sik_llms/mcp_manager.py
sik_llms/models_base.py
sik_llms/openai.py
sik_llms/reasoning_agent.py
sik_llms/telemetry.py
sik_llms/utilities.py
sik_llms/prompts/final_answer_prompt.txt
sik_llms/prompts/reasoning_prompt.txt
sik_llms-0.4.0.dist-info/METADATA
sik_llms-0.4.0.dist-info/WHEEL
sik_llms-0.4.0.dist-info/licenses/LICENSE
sik_llms-0.4.0.dist-info/RECORD
