Metadata-Version: 2.4
Name: sik-llms
Version: 0.4.0
Summary: Lightweight, easy, and consistent LLM-interface across providers and functionality.
License-File: LICENSE
Requires-Python: >=3.11
Requires-Dist: anthropic>=0.49.0
Requires-Dist: mcp[cli]>=1.5.0
Requires-Dist: nest-asyncio>=1.6.0
Requires-Dist: openai>=1.66.3
Requires-Dist: pydantic>=2.10.6
Requires-Dist: python-dotenv>=1.0.1
Requires-Dist: tiktoken>=0.9.0
